socketbridge/__init__.py
socketbridge/client.py
socketbridge/server.py
socketbridge-0.1.0.dist-info/licenses/LICENSE
socketbridge-0.1.0.dist-info/METADATA
socketbridge-0.1.0.dist-info/WHEEL
socketbridge-0.1.0.dist-info/top_level.txt
socketbridge-0.1.0.dist-info/RECORD
