Metadata-Version: 2.4
Name: socketbridge
Version: 0.1.0
Summary: Lightweight, stdlib-only TCP IPC bridge with length-prefixed JSON, loopback-by-default, auth tokens, allowlist, max-bytes cap, and protocol versioning.
Author: Eric Gilligan
License: MIT
Project-URL: Homepage, https://github.com/gillimo/SocketBridge
Project-URL: Repository, https://github.com/gillimo/SocketBridge
Classifier: Programming Language :: Python :: 3
Classifier: Programming Language :: Python :: 3 :: Only
Classifier: License :: OSI Approved :: MIT License
Classifier: Operating System :: OS Independent
Requires-Python: >=3.9
License-File: LICENSE
Dynamic: license-file
